spacy_symspell/__init__.py
spacy_symspell/about.py
spacy_symspell/frequency_dictionary_en_500_000.txt
spacy_symspell/frequency_dictionary_en_82_765.txt
spacy_symspell/spacy_symspell.py
spacy_symspell-0.1.2.dist-info/LICENSE
spacy_symspell-0.1.2.dist-info/METADATA
spacy_symspell-0.1.2.dist-info/WHEEL
spacy_symspell-0.1.2.dist-info/top_level.txt
spacy_symspell-0.1.2.dist-info/RECORD
