Metadata-Version: 2.1
Name: spacy-symspell
Version: 0.1.2
Summary: spaCy pipeline component for spelling correction using sysmepll.
Home-page: https://github.com/xwiz/spacy_symspell
Author: Xwiz
Author-email: c.opata@robosyslive.com
License: MIT
Platform: UNKNOWN
Classifier: Development Status :: 3 - Alpha
Classifier: Intended Audience :: Developers
Classifier: Natural Language :: English
Classifier: License :: OSI Approved :: MIT License
Classifier: Programming Language :: Python
Classifier: Programming Language :: Python :: 3
Classifier: Programming Language :: Python :: 3.5
Classifier: Programming Language :: Python :: 3.6
Classifier: Programming Language :: Python :: 3.7
Requires-Python: >=3.5
Requires-Dist: spacy (<3.0.0,>=2.0.0)
Requires-Dist: symspellpy (>=6.3.8)
